nanoslurm/__init__.py
nanoslurm/backend.py
nanoslurm/cli.py
nanoslurm/defaults.py
nanoslurm/job.py
nanoslurm/run.sh
nanoslurm/stats.py
nanoslurm/tui.py
nanoslurm/utils/__init__.py
nanoslurm/utils/cmd.py
nanoslurm-0.1.12.dist-info/METADATA
nanoslurm-0.1.12.dist-info/WHEEL
nanoslurm-0.1.12.dist-info/entry_points.txt
nanoslurm-0.1.12.dist-info/licenses/LICENSE
nanoslurm-0.1.12.dist-info/RECORD
