Metadata-Version: 2.4
Name: nanoslurm
Version: 0.1.12
Summary: Zero-dependency Python wrapper for SLURM job submission and monitoring
Author-email: Andrea Boscolo Camiletto <abcamiletto@gmail.com>
License-File: LICENSE
Classifier: Operating System :: POSIX :: Linux
Requires-Python: >=3.11
Requires-Dist: platformdirs
Requires-Dist: pyyaml
Requires-Dist: rich
Requires-Dist: textual
Requires-Dist: typer
